arabicprocess/__init__.py
arabicprocess/arabicpreprocessing.py
arabicprocess-1.0.dist-info/METADATA
arabicprocess-1.0.dist-info/WHEEL
arabicprocess-1.0.dist-info/licenses/LICENSE
arabicprocess-1.0.dist-info/RECORD
