Metadata-Version: 2.1
Name: arabicprocess
Version: 1.0
Summary: arabicprocess is a Python library designed to simplify and streamline the preprocessing of Arabic text data. It provides a collection of preprocessing methods, including data cleaning, stop word removal, and stemming, tailored specifically for Arabic language text.
Project-URL: Homepage, https://github.com/AhmedAldulaimi96/arabicprocess/
Project-URL: Bug Tracker, https://github.com/AhmedAldulaimi96/arabicprocess/issues/
Author-email: Ahmed Hashim Al-Dulaimi <ahmedhashimirq@gmail.com>
License-File: LICENSE
Classifier: License :: OSI Approved :: MIT License
Classifier: Operating System :: OS Independent
Classifier: Programming Language :: Python :: 3
Requires-Python: >=3.7
